vdlpy/__init__.py
vdlpy/parts.py
vdlpy/vdl.py
vdlpy/vdlcopy.py
vdlpy-2.1.0.dist-info/LICENSE
vdlpy-2.1.0.dist-info/METADATA
vdlpy-2.1.0.dist-info/WHEEL
vdlpy-2.1.0.dist-info/top_level.txt
vdlpy-2.1.0.dist-info/RECORD
