Metadata-Version: 2.1
Name: vdlpy
Version: 2.1.0
Summary: Python interface to virtual data lakes
Home-page: https://gitlab.com/vdl-open/pi/
Author: Chris Harding
Author-email: chris@lacibus.net
Project-URL: Documentation, https://vdl-open.gitlab.io/pi/vdlpy.html
Project-URL: Issue Tracker, https://gitlab.com/vdl-open/pi/-/issues
Classifier: Programming Language :: Python :: 3
Classifier: License :: OSI Approved :: GNU Lesser General Public License v2 (LGPLv2)
Classifier: Operating System :: OS Independent
Requires-Python: >=3.6
License-File: LICENSE
